cuda_histogram/__init__.py
cuda_histogram/_version.py
cuda_histogram/_version.pyi
cuda_histogram/hist.py
cuda_histogram/py.typed
cuda_histogram/axis/__init__.py
cuda_histogram-0.1.1.dist-info/METADATA
cuda_histogram-0.1.1.dist-info/WHEEL
cuda_histogram-0.1.1.dist-info/licenses/LICENSE
cuda_histogram-0.1.1.dist-info/RECORD
