Metadata-Version: 2.4
Name: cuda-histogram
Version: 0.1.1
Summary: Histogramming tools on CUDA.
Project-URL: Homepage, https://github.com/scikit-hep/cuda-histogram
Project-URL: Bug Tracker, https://github.com/scikit-hep/cuda-histogram/issues
Project-URL: Discussions, https://github.com/scikit-hep/cuda-histogram/discussions
Project-URL: Changelog, https://github.com/scikit-hep/cuda-histogram/releases
Author-email: Lindsey Gray <lagray@fnal.gov>, Saransh Chopra <saransh0701@gmail.com>
Maintainer-email: The Scikit-HEP admins <scikit-hep-admins@googlegroups.com>
License: BSD 3-Clause License
License-File: LICENSE
Classifier: Development Status :: 4 - Beta
Classifier: Intended Audience :: Developers
Classifier: Intended Audience :: Science/Research
Classifier: License :: OSI Approved :: BSD License
Classifier: Operating System :: OS Independent
Classifier: Programming Language :: Python
Classifier: Programming Language :: Python :: 3
Classifier: Programming Language :: Python :: 3 :: Only
Classifier: Programming Language :: Python :: 3.8
Classifier: Programming Language :: Python :: 3.9
Classifier: Programming Language :: Python :: 3.10
Classifier: Programming Language :: Python :: 3.11
Classifier: Programming Language :: Python :: 3.12
Classifier: Programming Language :: Python :: 3.13
Classifier: Topic :: Scientific/Engineering
Classifier: Typing :: Typed
Requires-Python: >=3.8
Requires-Dist: awkward>=2.6.3
Requires-Dist: boost-histogram
Requires-Dist: cupy-cuda12x>=13.1.0
Requires-Dist: hist>=2
Requires-Dist: numpy>=1.22.0
Requires-Dist: scipy>=1.1.0
Provides-Extra: dev
Requires-Dist: pre-commit; extra == 'dev'
Requires-Dist: pytest-cov>=3; extra == 'dev'
Requires-Dist: pytest-mpl; extra == 'dev'
Requires-Dist: pytest>=6; extra == 'dev'
Provides-Extra: docs
Requires-Dist: furo>=2023.08.17; extra == 'docs'
Requires-Dist: myst-parser>=0.13; extra == 'docs'
Requires-Dist: sphinx-autodoc-typehints; extra == 'docs'
Requires-Dist: sphinx-copybutton; extra == 'docs'
Requires-Dist: sphinx>=7.0; extra == 'docs'
